coir/__init__.py
coir/data_loader.py
coir/evaluation.py
coir/models.py
coir/utils.py
coir/beir/__init__.py
coir/beir/logging.py
coir/beir/util.py
coir/beir/datasets/__init__.py
coir/beir/datasets/data_loader.py
coir/beir/datasets/data_loader_hf.py
coir/beir/generation/__init__.py
coir/beir/generation/generate.py
coir/beir/generation/models/__init__.py
coir/beir/generation/models/auto_model.py
coir/beir/generation/models/tilde.py
coir/beir/losses/__init__.py
coir/beir/losses/bpr_loss.py
coir/beir/losses/margin_mse_loss.py
coir/beir/reranking/__init__.py
coir/beir/reranking/rerank.py
coir/beir/reranking/models/__init__.py
coir/beir/reranking/models/cross_encoder.py
coir/beir/reranking/models/mono_t5.py
coir/beir/retrieval/__init__.py
coir/beir/retrieval/custom_metrics.py
coir/beir/retrieval/evaluation.py
coir/beir/retrieval/train.py
coir/beir/retrieval/models/__init__.py
coir/beir/retrieval/models/bpr.py
coir/beir/retrieval/models/dpr.py
coir/beir/retrieval/models/sentence_bert.py
coir/beir/retrieval/models/sparta.py
coir/beir/retrieval/models/splade.py
coir/beir/retrieval/models/tldr.py
coir/beir/retrieval/models/unicoil.py
coir/beir/retrieval/models/use_qa.py
coir/beir/retrieval/search/__init__.py
coir/beir/retrieval/search/base.py
coir/beir/retrieval/search/dense/__init__.py
coir/beir/retrieval/search/dense/exact_search.py
coir/beir/retrieval/search/dense/exact_search_multi_gpu.py
coir/beir/retrieval/search/dense/faiss_index.py
coir/beir/retrieval/search/dense/faiss_search.py
coir/beir/retrieval/search/dense/util.py
coir/beir/retrieval/search/lexical/__init__.py
coir/beir/retrieval/search/lexical/bm25_search.py
coir/beir/retrieval/search/lexical/elastic_search.py
coir/beir/retrieval/search/sparse/__init__.py
coir/beir/retrieval/search/sparse/sparse_search.py
tests/__init__.py
tests/test_evaluation.py
coir_eval-0.7.0.dist-info/METADATA
coir_eval-0.7.0.dist-info/WHEEL
coir_eval-0.7.0.dist-info/top_level.txt
coir_eval-0.7.0.dist-info/RECORD
